setup.py
albumthief/__init__.py
albumthief/delegate.py
albumthief/fs.py
albumthief/manage.py
albumthief/multitask.py
albumthief/thief.py
albumthief.egg-info/PKG-INFO
albumthief.egg-info/SOURCES.txt
albumthief.egg-info/dependency_links.txt
albumthief.egg-info/entry_points.txt
albumthief.egg-info/requires.txt
albumthief.egg-info/top_level.txt