Metadata-Version: 1.1
Name: albumthief
Version: 0.1
Summary: Very fast album downloader made using gevent. 
Home-page: https://github.com/chaobin/albumthief
Author: Chaobin Tang
Author-email: cbtchn@gmail.com
License: GPLv2
Platform: UNKNOWN
Classifier: Programming Language :: Python :: 2.6
